setup.py
graphen/__init__.py
graphen/cli.py
graphen.egg-info/PKG-INFO
graphen.egg-info/SOURCES.txt
graphen.egg-info/dependency_links.txt
graphen.egg-info/entry_points.txt
graphen.egg-info/top_level.txt